nhl/__init__.py
nhl/main.py
nhl/utility/__init__.py
nhl/utility/constants.py
nhl/utility/decorators.py
nhl/utility/functions.py
nhl/utility/helpers.py
max_nhl_scraper-0.1.7.dist-info/METADATA
max_nhl_scraper-0.1.7.dist-info/WHEEL
max_nhl_scraper-0.1.7.dist-info/top_level.txt
max_nhl_scraper-0.1.7.dist-info/RECORD
